inquiry/__init__.py
inquiry/framework/__init__.py
inquiry/framework/bq.py
inquiry/framework/cli.py
inquiry/framework/gcp.py
inquiry/framework/local.py
inquiry/framework/task.py
inquiry/framework/util.py
inquiry/framework/viz.py
inquiry/framework/workflow.py
inquiry/iot/__init__.py
inquiry/services/__init__.py
inquiry/services/api.py
inquiry/services/base.py
inquiry/services/flow.py
inquiry/services/iot.py
inquiry/services/run.py
inquiry/toolkit/__init__.py
inquiry/toolkit/alignment/__init__.py
inquiry/toolkit/alignment/operations.py
inquiry/toolkit/alignment/workflow.py
inquiry/toolkit/genotyper_gatk/__init__.py
inquiry/toolkit/genotyper_gatk/operations.py
inquiry/toolkit/genotyper_gatk/workflow.py
inquiry/toolkit/metabolomics/__init__.py
inquiry/toolkit/metabolomics/operations.py
inquiry/toolkit/metabolomics/workflow.py
inquiry/toolkit/rna_quantification/__init__.py
inquiry/toolkit/rna_quantification/operations.py
inquiry/toolkit/rna_quantification/workflow.py
inquiry/tools/__init__.py
inquiry/tools/pip_package/__init__.py
inquiry/tools/pip_package/setup.py
iqtk-0.0.3.dist-info/DESCRIPTION.rst
iqtk-0.0.3.dist-info/METADATA
iqtk-0.0.3.dist-info/RECORD
iqtk-0.0.3.dist-info/WHEEL
iqtk-0.0.3.dist-info/entry_points.txt
iqtk-0.0.3.dist-info/metadata.json
iqtk-0.0.3.dist-info/top_level.txt
