Metadata-Version: 2.0
Name: iqtk
Version: 0.0.3
Summary: Reproducible biological data science.
Home-page: http://iqtk.io
Author: University of California
Author-email: inquiryproject@lists.lbl.gov
License: BSD-3
Keywords: inquiry genom proteom metabolom transcriptom
Platform: UNKNOWN
Classifier: Development Status :: 2 - Pre-Alpha
Classifier: Intended Audience :: Developers
Classifier: Intended Audience :: Education
Classifier: Intended Audience :: Science/Research
Classifier: License :: OSI Approved :: BSD License
Classifier: Programming Language :: Python :: 2.7
Classifier: Topic :: Software Development :: Libraries :: Python Modules
Classifier: Topic :: Software Development :: Libraries
Classifier: Topic :: Scientific/Engineering :: Bio-Informatics
Classifier: Topic :: Scientific/Engineering :: Information Analysis
Requires-Dist: click
Requires-Dist: coloredlogs
Requires-Dist: docker
Requires-Dist: flask
Requires-Dist: google-api-python-client
Requires-Dist: google-cloud-bigquery
Requires-Dist: google-cloud-dataflow
Requires-Dist: google-cloud-pubsub
Requires-Dist: protobuf
Requires-Dist: subprocess32
Requires-Dist: uritemplate
